{
    "biały": "#fff",
    "bialy": "#fff",
    "błękit": "#4169E1",
    "blekit": "#4169E1",
    "brązowy": "#964B00",
    "brazowy": "#964B00",
    "czarny": "#000000",
    "czekoladowy": "#8B4726",
    "czerwony": "#FF0000",
    "grafitowy": "#36454F",
    "granatowy": "#000080",
    "limonkowy": "#93F600",
    "niebieski": "#546eff",
    "różowy": "#FFC0CB",
    "rozowy": "#FFC0CB",
    "srebrny": "#C0C0C0",
    "szary": "#6c6c6c",
    "zielony": "#029802",
    "złoty": "#FFD700",
    "zloty": "#FFD700",
    "żółty": "#FFFF00",
    "zolty": "#FFFF00"
}